tabby_mcp/__init__.py
tabby_mcp/cdp.py
tabby_mcp/server.py
tabby_mcp/tools.py
tabby_mcp-0.1.0.dist-info/METADATA
tabby_mcp-0.1.0.dist-info/WHEEL
tabby_mcp-0.1.0.dist-info/entry_points.txt
tabby_mcp-0.1.0.dist-info/licenses/LICENSE
tabby_mcp-0.1.0.dist-info/RECORD
