Metadata-Version: 2.4
Name: tabby-mcp
Version: 0.1.0
Summary: MCP server for controlling Tabby terminal via Chrome DevTools Protocol
Project-URL: Homepage, https://github.com/halilc4/tabby-mcp
Project-URL: Repository, https://github.com/halilc4/tabby-mcp
Project-URL: Issues, https://github.com/halilc4/tabby-mcp/issues
Author-email: Igor Halilović <halilc4@gmail.com>
License-Expression: MIT
License-File: LICENSE
Keywords: cdp,chrome-devtools-protocol,mcp,tabby,terminal
Classifier: Development Status :: 3 - Alpha
Classifier: Intended Audience :: Developers
Classifier: License :: OSI Approved :: MIT License
Classifier: Programming Language :: Python :: 3
Classifier: Programming Language :: Python :: 3.10
Classifier: Programming Language :: Python :: 3.11
Classifier: Programming Language :: Python :: 3.12
Requires-Python: >=3.10
Requires-Dist: mcp>=1.0.0
Requires-Dist: pychrome>=0.2.4
